{
    "Ar36": {
        "error": 0.0026191631555178264, 
        "fit": "Linear", 
        "value": 0.8624676965265097
    }, 
    "Ar37": {
        "error": 0.0046807344680465665, 
        "fit": "linear", 
        "value": 0.028055262287847688
    }, 
    "Ar38": {
        "error": 0.01056462608444084, 
        "fit": "linear", 
        "value": 0.4969785475758737
    }, 
    "Ar39": {
        "error": 0.013568690841821388, 
        "fit": "Linear", 
        "value": 0.47303360261834393
    }, 
    "Ar40": {
        "error": 0.03167346698141139, 
        "fit": "Linear", 
        "value": 300.20238097121876
    }, 
    "Ar41": {
        "error": 0.005767349778968234, 
        "fit": "Average", 
        "value": 0.09902840485250418
    }
}