{
    "AX": {
        "error": 0.005788519216717281, 
        "filter_outliers_dict": {
            "filter_outliers": true, 
            "iterations": 1, 
            "std_devs": 2
        }, 
        "fit": "average", 
        "value": 0.04723921218321943
    }, 
    "CDD": {
        "error": 4.2596165329570076e-06, 
        "filter_outliers_dict": {
            "filter_outliers": true, 
            "iterations": 1, 
            "std_devs": 10
        }, 
        "fit": "average", 
        "value": 7.506192697621149e-06
    }, 
    "H1": {
        "error": 0.004393283859611491, 
        "filter_outliers_dict": {
            "filter_outliers": true, 
            "iterations": 1, 
            "std_devs": 2
        }, 
        "fit": "average", 
        "value": -0.04524439784974477
    }, 
    "H2": {
        "error": 0.006153449674357213, 
        "filter_outliers_dict": {
            "filter_outliers": true, 
            "iterations": 1, 
            "std_devs": 2
        }, 
        "fit": "average", 
        "value": 0.08079974214137386
    }, 
    "L1": {
        "error": 0.0061404902834993665, 
        "filter_outliers_dict": {
            "filter_outliers": true, 
            "iterations": 1, 
            "std_devs": 2
        }, 
        "fit": "average", 
        "value": 0.12456697673577703
    }, 
    "L2": {
        "error": 0.0021805460092721727, 
        "filter_outliers_dict": {
            "filter_outliers": true, 
            "iterations": 1, 
            "std_devs": 2
        }, 
        "fit": "average", 
        "value": 0.0042961059734588
    }
}